MANIFEST.in
README.txt
setup.py
collective/__init__.py
collective.action.twitter.egg-info/PKG-INFO
collective.action.twitter.egg-info/SOURCES.txt
collective.action.twitter.egg-info/dependency_links.txt
collective.action.twitter.egg-info/entry_points.txt
collective.action.twitter.egg-info/namespace_packages.txt
collective.action.twitter.egg-info/not-zip-safe
collective.action.twitter.egg-info/requires.txt
collective.action.twitter.egg-info/top_level.txt
collective/action/__init__.py
collective/action/twitter/__init__.py
collective/action/twitter/configure.zcml
collective/action/twitter/tests.py
collective/action/twitter/twitteraction.py
collective/action/twitter/version.txt
docs/HISTORY.txt
docs/INSTALL.txt
docs/LICENSE.GPL
docs/LICENSE.txt