Metadata-Version: 1.0
Name: collective.action.twitter
Version: 0.2
Summary: A contentrule action to publish something on twitter.
Home-page: http://www.catworkx.de
Author: Hanno Schulz
Author-email: hanno.schulz@catworkx.de
License: GPL
Platform: UNKNOWN
Classifier: Framework :: Plone
Classifier: Programming Language :: Python
Classifier: Topic :: Software Development :: Libraries :: Python Modules
